pybibtexer/.python-version
pybibtexer/Main.sublime-menu
pybibtexer/__init__.py
pybibtexer/pybibtexer.sublime-settings
pybibtexer/pybibtexer.sublime-syntax
pybibtexer/bib/__init__.py
pybibtexer/bib/bibtexbase/__init__.py
pybibtexer/bib/bibtexbase/standardize_bib.py
pybibtexer/bib/bibtexbase/standardize/__init__.py
pybibtexer/bib/bibtexbase/standardize/_base.py
pybibtexer/bib/bibtexbase/standardize/default_data.py
pybibtexer/bib/bibtexbase/standardize/do_on_bib.py
pybibtexer/bib/bibtexbase/standardize/do_on_comment_block.py
pybibtexer/bib/bibtexbase/standardize/do_on_entry_block.py
pybibtexer/bib/bibtexbase/standardize/do_on_preamble_block.py
pybibtexer/bib/bibtexbase/standardize/do_on_string_block.py
pybibtexer/bib/bibtexparser/__init__.py
pybibtexer/bib/bibtexparser/bibtex_format.py
pybibtexer/bib/bibtexparser/exceptions.py
pybibtexer/bib/bibtexparser/library.py
pybibtexer/bib/bibtexparser/middlewares_library_to_library.py
pybibtexer/bib/bibtexparser/middlewares_library_to_str.py
pybibtexer/bib/bibtexparser/middlewares_str_to_library.py
pybibtexer/bib/bibtexparser/middlewares_str_to_str.py
pybibtexer/bib/bibtexparser/model.py
pybibtexer/bib/bibtexparser/splitter.py
pybibtexer/bib/bibtexparser/middlewares/__init__.py
pybibtexer/bib/bibtexparser/middlewares/middleware.py
pybibtexer/bib/bibtexparser/middlewares/parsestack.py
pybibtexer/bib/bibtexparser/middlewares/utils.py
pybibtexer/bib/bibtexparser/middlewares/block/__init__.py
pybibtexer/bib/bibtexparser/middlewares/block/add_field.py
pybibtexer/bib/bibtexparser/middlewares/block/authors.py
pybibtexer/bib/bibtexparser/middlewares/block/doi_url.py
pybibtexer/bib/bibtexparser/middlewares/block/entry_field_keys_normalize.py
pybibtexer/bib/bibtexparser/middlewares/block/entry_field_keys_replace.py
pybibtexer/bib/bibtexparser/middlewares/block/entry_field_values_normalize.py
pybibtexer/bib/bibtexparser/middlewares/block/entry_fields_delete.py
pybibtexer/bib/bibtexparser/middlewares/block/entry_fields_keep.py
pybibtexer-0.3.29.dist-info/METADATA
pybibtexer-0.3.29.dist-info/WHEEL
pybibtexer-0.3.29.dist-info/licenses/LICENSE
pybibtexer-0.3.29.dist-info/RECORD
