Metadata-Version: 2.4
Name: pybibtexer
Version: 0.3.29
Summary: pybibtexer
Project-URL: Homepage, https://github.com/Easy-PhD/pybibtexer
Project-URL: Repository, https://github.com/Easy-PhD/pybibtexer
Project-URL: Documentation, https://Easy-PhD.github.io/pybibtexer
Project-URL: Source, https://github.com/Easy-PhD/pybibtexer
Project-URL: Issues, https://github.com/Easy-PhD/pybibtexer/issues
Project-URL: Changelog, https://github.com/Easy-PhD/pybibtexer/releases
Author-email: NextAI <nextartifintell@gmail.com>
Maintainer-email: NextAI <nextartifintell@gmail.com>
License-Expression: GPL-3.0-or-later
License-File: LICENSE
Keywords: BibTex,Python
Classifier: Operating System :: OS Independent
Classifier: Programming Language :: Python
Classifier: Programming Language :: Python :: 3
Classifier: Programming Language :: Python :: 3.12
Classifier: Programming Language :: Python :: 3.13
Classifier: Programming Language :: Python :: 3.14
Classifier: Topic :: Software Development :: Libraries :: Python Modules
Requires-Python: >=3.12
Requires-Dist: pyadvtools>=0.3.10
